PyWebRequests/__init__.py
PyWebRequests/proxies.py
PyWebRequests/user_agents/__init__.py
PyWebRequests/user_agents/data.py
PyWebRequests/user_agents/data_types.py
PyWebRequests-1.3.13.dist-info/METADATA
PyWebRequests-1.3.13.dist-info/WHEEL
PyWebRequests-1.3.13.dist-info/top_level.txt
PyWebRequests-1.3.13.dist-info/RECORD
