Metadata-Version: 2.2
Name: PyWebRequests
Version: 1.3.13
Summary: PyWebRequests simplifies web scraping and requests in Python. It provides easy-to-use functions for fetching HTML, finding web elements using XPath, managing proxies, and generating random user agents.
Author: oddshellnick
Author-email: oddshellnick.programming@gmail.com
Requires-Dist: setuptools
Requires-Dist: requests~=2.32.3
Requires-Dist: lxml~=5.3.0
Requires-Dist: bs4~=0.0.2
Requires-Dist: beautifulsoup4~=4.12.3
Dynamic: author
Dynamic: author-email
Dynamic: description
Dynamic: description-content-type
Dynamic: requires-dist
Dynamic: summary
